cdio_amazon_restock_price_scraper/__init__.py
cdio_amazon_restock_price_scraper/plugin.py
changedetection.io_amazon_price_scraper-0.35.dist-info/LICENSE
changedetection.io_amazon_price_scraper-0.35.dist-info/METADATA
changedetection.io_amazon_price_scraper-0.35.dist-info/WHEEL
changedetection.io_amazon_price_scraper-0.35.dist-info/entry_points.txt
changedetection.io_amazon_price_scraper-0.35.dist-info/top_level.txt
changedetection.io_amazon_price_scraper-0.35.dist-info/RECORD
