Metadata-Version: 2.1
Name: changedetection.io-amazon-price-scraper
Version: 0.35
Home-page: https://changedetection.io
Author: dgtlmoon
Author-email: dgtlmoon@gmail.com
Keywords: amazon price restock detection notification price change alerts
Requires-Python: >= 3.10
License-File: LICENSE
Requires-Dist: changedetection.io
